mistral_ocr_mcp/__init__.py
mistral_ocr_mcp/__main__.py
mistral_ocr_mcp/config.py
mistral_ocr_mcp/extraction.py
mistral_ocr_mcp/images.py
mistral_ocr_mcp/markdown_rewrite.py
mistral_ocr_mcp/mistral_client.py
mistral_ocr_mcp/path_sandbox.py
mistral_ocr_mcp/server.py
mistral_ocr_mcp-0.1.7.dist-info/METADATA
mistral_ocr_mcp-0.1.7.dist-info/WHEEL
mistral_ocr_mcp-0.1.7.dist-info/entry_points.txt
mistral_ocr_mcp-0.1.7.dist-info/licenses/LICENSE
mistral_ocr_mcp-0.1.7.dist-info/RECORD
