Metadata-Version: 2.4
Name: mistral-ocr-mcp
Version: 0.1.7
Summary: MCP server for extracting text and images from documents using Mistral OCR API
Project-URL: Homepage, https://github.com/ORDIS-Co-Ltd/mistral-ocr-mcp
Project-URL: Repository, https://github.com/ORDIS-Co-Ltd/mistral-ocr-mcp
Author: ORDIS Co., Ltd.
License: MIT License
License-File: LICENSE
Requires-Dist: mcp>=1.0.0
Requires-Dist: mistralai>=1.0.0
Provides-Extra: dev
Requires-Dist: pytest>=8.0.0; extra == 'dev'
